lizahwlib/__init__.py
lizahwlib/ast_graph.py
lizahwlib/fibonacci.py
lizahwlib/main.py
lizahwlib-0.0.1.dist-info/METADATA
lizahwlib-0.0.1.dist-info/WHEEL
lizahwlib-0.0.1.dist-info/top_level.txt
lizahwlib-0.0.1.dist-info/RECORD
